onlyfirst/__init__.py
onlyfirst/__main__.py
onlyfirst/onlyfirst.py
onlyfirst-0.1.2.dist-info/entry_points.txt
onlyfirst-0.1.2.dist-info/WHEEL
onlyfirst-0.1.2.dist-info/METADATA
onlyfirst-0.1.2.dist-info/RECORD
