Metadata-Version: 2.1
Name: onlyfirst
Version: 0.1.2
Summary: only first word remains
Author: svtter
Author-email: svtter@qq.com
Requires-Python: >=3.7
Classifier: Programming Language :: Python :: 3
Classifier: Programming Language :: Python :: 3.10
Classifier: Programming Language :: Python :: 3.7
Classifier: Programming Language :: Python :: 3.8
Classifier: Programming Language :: Python :: 3.9
